<?xml version="1.0" encoding="UTF-8"?>
<!--
  ~ Copyright (c) 2010-2017 Evolveum and contributors
  ~
  ~ This work is dual-licensed under the Apache License 2.0
  ~ and European Union Public License. See LICENSE file for details.
  -->
<task oid="00000000-0000-0000-0000-000000000005"
      xmlns="http://midpoint.evolveum.com/xml/ns/public/common/common-3">

    <name>Cleanup</name>
    <description>A system task that repeatedly checks for outdated objects (e.g. closed tasks, old audit records) and removes them.</description>
    <assignment>
        <targetRef oid="00000000-0000-0000-0000-000000000506" type="ArchetypeType" />
    </assignment>
    <ownerRef oid="00000000-0000-0000-0000-000000000002" type="UserType"/>
    <executionState>runnable</executionState>

    <binding>loose</binding>
    <schedule>
        <interval>86400</interval>
    </schedule>

    <activity>
        <work>
            <cleanup/>
        </work>
    </activity>
</task>
