<?xml version="1.0" encoding="UTF-8"?>
<!--
  ~ Copyright (c) 2010-2017 Evolveum
  ~
  ~ Licensed under the Apache License, Version 2.0 (the "License");
  ~ you may not use this file except in compliance with the License.
  ~ You may obtain a copy of the License at
  ~
  ~     http://www.apache.org/licenses/LICENSE-2.0
  ~
  ~ Unless required by applicable law or agreed to in writing, software
  ~ distributed under the License is distributed on an "AS IS" BASIS,
  ~ WITHOUT WARRANTIES OR CONDITIONS OF ANY KIND, either express or implied.
  ~ See the License for the specific language governing permissions and
  ~ limitations under the License.
  -->

<beans xmlns="http://www.springframework.org/schema/beans"
             xmlns:xsi="http://www.w3.org/2001/XMLSchema-instance"
             xsi:schemaLocation="http://www.springframework.org/schema/beans http://www.springframework.org/schema/beans/spring-beans-4.1.xsd">


	<!-- For SSO CAS integration uncomment following and set CASSERVER address   and   change service url according to your needs-->
	<!-- CAS CONFIG -->
	<bean id="serviceProperties"
        class="org.springframework.security.cas.ServiceProperties">
    <property name="service"
        value="${auth.cas.midpoint.host}/j_spring_cas_security_check"/>
    <property name="sendRenew" value="${auth.cas.send.renew}"/>
  </bean>
  
  <bean id="casFilter"
        class="org.springframework.security.cas.web.CasAuthenticationFilter">
    <property name="authenticationManager" ref="authenticationManager"/>
  </bean>

  <bean id="casEntryPoint"
      class="org.springframework.security.cas.web.CasAuthenticationEntryPoint">
    <property name="loginUrl" value="${auth.cas.server.host}/cas/login"/>
    <property name="serviceProperties" ref="serviceProperties"/>
  </bean>
  
  <bean id="midPointAuthenticationProvider"
      class="org.springframework.security.cas.authentication.CasAuthenticationProvider">
    <property name="authenticationUserDetailsService">
      <bean class="org.springframework.security.core.userdetails.UserDetailsByNameServiceWrapper">
        <constructor-arg ref="userDetailsService" />
      </bean>
    </property>
    <property name="serviceProperties" ref="serviceProperties" />
    <property name="ticketValidator">
      <bean class="org.jasig.cas.client.validation.Cas20ServiceTicketValidator">
        <constructor-arg index="0" value="${auth.cas.server.host}/cas" />
      </bean>
    </property>
    <property name="key" value="CAS_ID"/>
  </bean>
 

	<!-- For SLO CAS integration uncomment following and set CASSERVER address-->
	<!-- LOGOUT -->
	
  <!-- This filter handles a Single Logout Request from the CAS Server -->
  <bean id="singleLogoutFilter" class="org.jasig.cas.client.session.SingleSignOutFilter"/>
  
  <!-- This filter redirects to the CAS Server to signal Single Logout should be performed -->

	<bean id="requestSingleLogoutFilter"
        class="org.springframework.security.web.authentication.logout.LogoutFilter">
    <constructor-arg value="${auth.cas.server.host}/cas/logout"/>
    <constructor-arg>
      <bean class=
          "org.springframework.security.web.authentication.logout.SecurityContextLogoutHandler"/>
    </constructor-arg>
    <property name="filterProcessesUrl" value="/j_spring_cas_security_logout"/>
  </bean>  
  
</beans>
