<?xml version="1.0" encoding="UTF-8"?>
<!--
  ~ Copyright (c) 2010-2013 Evolveum
  ~
  ~ Licensed under the Apache License, Version 2.0 (the "License");
  ~ you may not use this file except in compliance with the License.
  ~ You may obtain a copy of the License at
  ~
  ~     http://www.apache.org/licenses/LICENSE-2.0
  ~
  ~ Unless required by applicable law or agreed to in writing, software
  ~ distributed under the License is distributed on an "AS IS" BASIS,
  ~ WITHOUT WARRANTIES OR CONDITIONS OF ANY KIND, either express or implied.
  ~ See the License for the specific language governing permissions and
  ~ limitations under the License.
  -->

<groups xmlns="http://www.isdc.ro/wro">
    <!-- this group is obsolete, will be removed -->
    <group name="all">
        <css>/less/config.less</css>
        <css>/less/evolveum-obsolete.less</css>
        <css>/less/global.less</css>
        <css>/WEB-INF/classes/com/evolveum/midpoint/web/component/assignment/AssignmentHeaderPanel.less</css>
        <css>/WEB-INF/classes/com/evolveum/midpoint/web/page/admin/home/PageMyPasswords.less</css>
    </group>

    <group name="bootstrap">
        <css>/less/bootstrap/bootstrap.less</css>
        <!-- must be enumerated for proper order -->
        <js>/js/bootstrap/transition.js</js>
        <js>/js/bootstrap/alert.js</js>
        <js>/js/bootstrap/button.js</js>
        <js>/js/bootstrap/carousel.js</js>
        <js>/js/bootstrap/collapse.js</js>
        <js>/js/bootstrap/dropdown.js</js>
        <js>/js/bootstrap/modal.js</js>
        <js>/js/bootstrap/tooltip.js</js>
        <js>/js/bootstrap/popover.js</js>
        <js>/js/bootstrap/scrollspy.js</js>
        <js>/js/bootstrap/tab.js</js>
        <js>/js/bootstrap/affix.js</js>
    </group>

    <group name="bootstrap-override">
        <css>/less/midpoint/bootstrap-override.less</css>
    </group>

    <group name="midpoint">
        <css>/less/midpoint/midpoint.less</css>
        <js>/js/midpoint/ace-editor.js</js>
        <js>/js/midpoint/dropdown-multiple.js</js>
        <js>/js/midpoint/midpoint.js</js>
    </group>
</groups>
